src/__init__.py
src/pbixray_server.py
iflow_mcp_pbixray_mcp_server-0.1.0.dist-info/METADATA
iflow_mcp_pbixray_mcp_server-0.1.0.dist-info/WHEEL
iflow_mcp_pbixray_mcp_server-0.1.0.dist-info/entry_points.txt
iflow_mcp_pbixray_mcp_server-0.1.0.dist-info/licenses/LICENSE
iflow_mcp_pbixray_mcp_server-0.1.0.dist-info/RECORD
